{"test_image/lr_0.0002_steps_4000_rank_16/An HCON, a black and white minimalist icon of that represents a bank account":{"_type":"image-file","sha256":"8bcdad198f1f1d23044c71fbc3d3dc01805a2a92fc51a046aa4757f053c8f367","size":210581,"path":"media/images/test_image/lr_0.0002_steps_4000_rank_16/An HCON, a black and white minimalist icon of that represents a bank account_4_8bcdad198f1f1d23044c.png","format":"png","width":1024,"height":1024},"test_image/lr_0.0002_steps_4000_rank_16/An HCON, a black and white minimalist icon that represents the international monetary system":{"format":"png","width":1024,"height":1024,"_type":"image-file","sha256":"286163ca00b2c7b7854a3ba2347f4d7e4515f57805de9a2f8ea45cd9716e2bd1","size":201850,"path":"media/images/test_image/lr_0.0002_steps_4000_rank_16/An HCON, a black and white minimalist icon that represents the international monetary system_0_286163ca00b2c7b7854a.png"},"_timestamp":1.731881859609544e+09,"_step":4,"test_image/lr_0.0002_steps_4000_rank_16/An HCON, a black and white minimalist icon of a macbook pro laptop":{"height":1024,"_type":"image-file","sha256":"7e4220db0c2d8d2ea589ca0c7644b41d1da146e859bec25de0766e117c1a575c","size":135267,"path":"media/images/test_image/lr_0.0002_steps_4000_rank_16/An HCON, a black and white minimalist icon of a macbook pro laptop_1_7e4220db0c2d8d2ea589.png","format":"png","width":1024},"_runtime":67.619437,"test_image/lr_0.0002_steps_4000_rank_16/An HCON, a black and white minimalist icon of a tiara":{"size":230929,"path":"media/images/test_image/lr_0.0002_steps_4000_rank_16/An HCON, a black and white minimalist icon of a tiara_2_0d06b6256296e7d49cb1.png","format":"png","width":1024,"height":1024,"_type":"image-file","sha256":"0d06b6256296e7d49cb19b8eb72ffe14d01d450c0d451c11f4bb69d8036af54a"},"test_image/lr_0.0002_steps_4000_rank_16/An HCON, a black and white minimalist icon of mountain peaks":{"_type":"image-file","sha256":"fd3bdb0db0ea71d22da0b92482e13dd437d9c8317d754ca22d23c6e0e8b1302f","size":188918,"path":"media/images/test_image/lr_0.0002_steps_4000_rank_16/An HCON, a black and white minimalist icon of mountain peaks_3_fd3bdb0db0ea71d22da0.png","format":"png","width":1024,"height":1024},"_wandb":{"runtime":67}}